Chapter 4/decode.sv
module decode(
  input [31:0] instruction,
  output reg is_b,
  output reg is_i,
  output reg is_j,
  output reg is_r,
  output reg is_s,
  output reg is_u,
  output reg incorrect
  );

  logic funct3, rd, rs1, rs2, opcode, imm;
  logic valid_funct3, valid_rd, valid_rs1, valid_rs2, valid_imm;
  

  always_comb begin
    is_b = 1'b0;
    is_i = 1'b0;
    is_j = 1'b0;
    is_r = 1'b0;
    is_s = 1'b0;
    is_u = 1'b0;
    incorrect = 1'b0;

    case (instruction[1:0]) 
      2'b11: begin
        incorrect = 1'b0;

        case (instruction[6:5]) 
          2'b00: begin
            case(instruction[4:2]) 
              3'b000, 3'b001, 3'b100, 3'b110: is_i = 1'b1;
              3'b101: is_u = 1'b1;
              default: incorrect = 1'b1;
            endcase
          end

          2'b01: begin
            case(instruction[4:2]) 
              3'b000, 3'b001: is_s = 1'b1;
              3'b011, 3'b100, 3'b110: is_r = 1'b1;
              3'b101: is_u = 1'b1;
              default: incorrect = 1'b1;
            endcase
          end

          2'b10: begin
            case(instruction[4:2])
              3'b100: is_r = 1'b1;
              default: incorrect = 1'b1;
            endcase
          end

          2'b11: begin
            case(instruction[4:2]) 
              3'b000:is_b = 1'b1;
              3'b001:is_i = 1'b1;
              3'b011:is_j = 1'b1;
              default: incorrect = 1'b1;
            endcase
          end

          default: incorrect = 1'b1;
        endcase
      end

      default: incorrect = 1'b1;
    endcase

    // Field extraction
    assign rs2 = instruction[24:20];
    assign rs1 = instruction[19:15];
    assign rd = instruction[11:7];
    assign opcode = instruction[6:0];

    // Validity of fields
    assign valid_funct3 = (is_b || is_i || is_r || is_s) ? 1'b1 : 1'b0;
    assign valid_rd = (is_r || is_i || is_u || is_j) ? 1'b1 : 1'b0;
    assign valid_rs1 = (is_r || is_i || is_s || is_b) ? 1'b1 : 1'b0;
    assign valid_rs2 = (is_r || is_s || is_b) ? 1'b1 : 1'b0;
    assign valid_imm = (is_i || is_s || is_b || is_u || is_j) ? 1'b1 : 1'b0

    assign imm = is_i ? {21{instruction[31]}, instruction[30:20]} :
                 is_s ? {} :
                 is_b ? {} :
                 is_u ? {} :
                 is_j ? {} : 0;

    
  end

endmodule

Chapter 4/tb_decode.sv
`include "decode.sv"

module tb_decode();
  reg [31:0] instruction;
  wire is_b, is_i, is_j, is_r, is_s, is_u, incorrect;
  
  decode uut (
    .instruction(instruction), 
    .is_b(is_b),
    .is_i(is_i),
    .is_j(is_j),
    .is_r(is_r),
    .is_s(is_s),
    .is_u(is_u),
    .incorrect(incorrect)
  );

  initial begin
    // Generate 10 random instructions
    repeat (10) begin
      instruction = $random;
      #1;
    end
  end

  initial begin
    $dumpfile("tb_decode.vcd");
    $dumpvars(0, tb_decode);
  end
endmodule

Chapter 4/tb_decode.vcd
$date
	Mon Oct 14 09:20:43 2024
$end
$version
	Icarus Verilog
$end
$timescale
	1s
$end
$scope module tb_decode $end
$var wire 1 ! is_u $end
$var wire 1 " is_s $end
$var wire 1 # is_r $end
$var wire 1 $ is_j $end
$var wire 1 % is_i $end
$var wire 1 & is_b $end
$var wire 1 ' incorrect $end
$var reg 32 ( instruction [31:0] $end
$scope module uut $end
$var wire 32 ) instruction [31:0] $end
$var reg 1 ' incorrect $end
$var reg 1 & is_b $end
$var reg 1 % is_i $end
$var reg 1 $ is_j $end
$var reg 1 # is_r $end
$var reg 1 " is_s $end
$var reg 1 ! is_u $end
$upscope $end
$upscope $end
$enddefinitions $end
$comment Show the parameter values. $end
$dumpall
$end
#0
$dumpvars
b10010000101010011010100100100 )
b10010000101010011010100100100 (
1'
0&
0%
0$
0#
0"
0!
$end
#1
1'
b11000000100010010101111010000001 (
b11000000100010010101111010000001 )
#2
1'
b10000100100001001101011000001001 (
b10000100100001001101011000001001 )
#3
1&
0'
b10110001111100000101011001100011 (
b10110001111100000101011001100011 )
#4
1'
0&
b110101110010111101100001101 (
b110101110010111101100001101 )
#5
1'
b1000110110111111001100110001101 (
b1000110110111111001100110001101 )
#6
1'
b10110010110000101000010001100101 (
b10110010110000101000010001100101 )
#7
1'
b10001001001101110101001000010010 (
b10001001001101110101001000010010 )
#8
1'
b111100111110001100000001 (
b111100111110001100000001 )
#9
1'
b110110101111100110100001101 (
b110110101111100110100001101 )
